st7735_tft/__init__.py
st7735_tft/st7735_tft.py
st7735_tft-1.0.dist-info/LICENSE
st7735_tft-1.0.dist-info/METADATA
st7735_tft-1.0.dist-info/WHEEL
st7735_tft-1.0.dist-info/top_level.txt
st7735_tft-1.0.dist-info/RECORD
