Metadata-Version: 2.1
Name: st7735-tft
Version: 1.0
Summary: Python library for controlling ST7735 based displays
Home-page: https://github.com/Frederic98/st7735_tft
Author: Frederic
License: UNKNOWN
Platform: UNKNOWN
Classifier: Programming Language :: Python :: 3
Classifier: License :: OSI Approved :: MIT License
Classifier: Operating System :: OS Independent
Requires-Python: >=3.6
